utils/__init__.py
utils/check_python.py
utils/format_markdown.py
utils/format_yaml.py
utils/lint.py
utils/validate_docker.py
utils/verify_build.py
utils/verify_docker.py
cve_report_aggregator/__init__.py
cve_report_aggregator/__main__.py
cve_report_aggregator/cli.py
cve_report_aggregator/context.py
cve_report_aggregator/utils.py
cve_report_aggregator/core/__init__.py
cve_report_aggregator/core/config.py
cve_report_aggregator/core/constants.py
cve_report_aggregator/core/error_handler.py
cve_report_aggregator/core/exceptions.py
cve_report_aggregator/core/executor.py
cve_report_aggregator/core/json_utils.py
cve_report_aggregator/core/logging.py
cve_report_aggregator/core/models.py
cve_report_aggregator/core/orchestrator.py
cve_report_aggregator/core/validation.py
cve_report_aggregator/enhance/__init__.py
cve_report_aggregator/enhance/base.py
cve_report_aggregator/enhance/baseline_security_context.md
cve_report_aggregator/enhance/exceptions.py
cve_report_aggregator/enhance/factory.py
cve_report_aggregator/enhance/models.py
cve_report_aggregator/enhance/providers/__init__.py
cve_report_aggregator/enhance/providers/mock.py
cve_report_aggregator/enhance/providers/openrouter.py
cve_report_aggregator/io/__init__.py
cve_report_aggregator/io/archive.py
cve_report_aggregator/io/csv_export.py
cve_report_aggregator/io/downloader.py
cve_report_aggregator/io/local_packages.py
cve_report_aggregator/io/report.py
cve_report_aggregator/processing/__init__.py
cve_report_aggregator/processing/aggregator.py
cve_report_aggregator/processing/parallel_scanner.py
cve_report_aggregator/processing/pipeline.py
cve_report_aggregator/processing/scanner.py
cve_report_aggregator/processing/scanner_tools.py
cve_report_aggregator/processing/severity.py
cve_report_aggregator-0.19.8.dist-info/METADATA
cve_report_aggregator-0.19.8.dist-info/WHEEL
cve_report_aggregator-0.19.8.dist-info/entry_points.txt
cve_report_aggregator-0.19.8.dist-info/licenses/LICENSE
cve_report_aggregator-0.19.8.dist-info/RECORD
