Metadata-Version: 2.4
Name: cve-report-aggregator
Version: 0.19.8
Summary: Aggregate and deduplicate vulnerability scan reports from Grype and Trivy
Project-URL: Homepage, https://github.com/mkm29/cve-report-aggregator
Project-URL: Repository, https://github.com/mkm29/cve-report-aggregator
Project-URL: Issues, https://github.com/mkm29/cve-report-aggregator/issues
Author-email: Mitchell Murphy <mitchell.murphy@defenseunicorns.com>
License: MIT
License-File: LICENSE
Keywords: cve,grype,sbom,security,trivy,vulnerability
Classifier: Development Status :: 4 - Beta
Classifier: Environment :: Console
Classifier: Intended Audience :: Developers
Classifier: Intended Audience :: System Administrators
Classifier: License :: OSI Approved :: MIT License
Classifier: Operating System :: OS Independent
Classifier: Programming Language :: Python :: 3
Classifier: Programming Language :: Python :: 3.14
Classifier: Topic :: Security
Classifier: Topic :: Software Development :: Quality Assurance
Requires-Python: >=3.14
Requires-Dist: aiofiles==25.1.0
Requires-Dist: click==8.3.1
Requires-Dist: openai[aiohttp]==2.14.0
Requires-Dist: openrouter>=0.1.1
Requires-Dist: pydantic-settings==2.12.0
Requires-Dist: pydantic==2.12.5
Requires-Dist: pyyaml==6.0.3
Requires-Dist: rich-click==1.9.5
Requires-Dist: rich==14.2.0
Requires-Dist: structlog==25.5.0
Provides-Extra: dev
Requires-Dist: pytest-cov==7.0.0; extra == 'dev'
Requires-Dist: pytest==9.0.2; extra == 'dev'
Requires-Dist: ruff==0.14.10; extra == 'dev'
Requires-Dist: ty==0.0.6; extra == 'dev'
